skyset/__init__.py
skyset-0.1.0.dist-info/METADATA
skyset-0.1.0.dist-info/WHEEL
skyset-0.1.0.dist-info/entry_points.txt
skyset-0.1.0.dist-info/RECORD
